[
  {
    "post_wp_id": 196,
    "tag_wp_id": 26
  },
  {
    "post_wp_id": 228,
    "tag_wp_id": 23
  },
  {
    "post_wp_id": 262,
    "tag_wp_id": 56
  },
  {
    "post_wp_id": 396,
    "tag_wp_id": 55
  },
  {
    "post_wp_id": 417,
    "tag_wp_id": 13
  },
  {
    "post_wp_id": 548,
    "tag_wp_id": 30
  },
  {
    "post_wp_id": 568,
    "tag_wp_id": 57
  },
  {
    "post_wp_id": 605,
    "tag_wp_id": 58
  },
  {
    "post_wp_id": 632,
    "tag_wp_id": 45
  },
  {
    "post_wp_id": 669,
    "tag_wp_id": 28
  },
  {
    "post_wp_id": 762,
    "tag_wp_id": 25
  },
  {
    "post_wp_id": 784,
    "tag_wp_id": 20
  },
  {
    "post_wp_id": 830,
    "tag_wp_id": 59
  },
  {
    "post_wp_id": 887,
    "tag_wp_id": 60
  },
  {
    "post_wp_id": 909,
    "tag_wp_id": 61
  },
  {
    "post_wp_id": 972,
    "tag_wp_id": 37
  },
  {
    "post_wp_id": 1019,
    "tag_wp_id": 62
  },
  {
    "post_wp_id": 1142,
    "tag_wp_id": 71
  },
  {
    "post_wp_id": 1196,
    "tag_wp_id": 72
  },
  {
    "post_wp_id": 1326,
    "tag_wp_id": 32
  },
  {
    "post_wp_id": 1403,
    "tag_wp_id": 18
  },
  {
    "post_wp_id": 1553,
    "tag_wp_id": 27
  },
  {
    "post_wp_id": 1582,
    "tag_wp_id": 80
  },
  {
    "post_wp_id": 1612,
    "tag_wp_id": 13
  },
  {
    "post_wp_id": 1612,
    "tag_wp_id": 83
  },
  {
    "post_wp_id": 1652,
    "tag_wp_id": 84
  },
  {
    "post_wp_id": 1652,
    "tag_wp_id": 85
  },
  {
    "post_wp_id": 1664,
    "tag_wp_id": 36
  },
  {
    "post_wp_id": 1664,
    "tag_wp_id": 86
  },
  {
    "post_wp_id": 1693,
    "tag_wp_id": 87
  },
  {
    "post_wp_id": 1693,
    "tag_wp_id": 88
  },
  {
    "post_wp_id": 1712,
    "tag_wp_id": 89
  },
  {
    "post_wp_id": 1712,
    "tag_wp_id": 90
  },
  {
    "post_wp_id": 1712,
    "tag_wp_id": 91
  },
  {
    "post_wp_id": 1747,
    "tag_wp_id": 92
  },
  {
    "post_wp_id": 1747,
    "tag_wp_id": 93
  },
  {
    "post_wp_id": 1766,
    "tag_wp_id": 96
  },
  {
    "post_wp_id": 1766,
    "tag_wp_id": 97
  },
  {
    "post_wp_id": 1773,
    "tag_wp_id": 72
  },
  {
    "post_wp_id": 1773,
    "tag_wp_id": 94
  },
  {
    "post_wp_id": 1853,
    "tag_wp_id": 98
  },
  {
    "post_wp_id": 1853,
    "tag_wp_id": 99
  },
  {
    "post_wp_id": 1948,
    "tag_wp_id": 100
  },
  {
    "post_wp_id": 1948,
    "tag_wp_id": 101
  },
  {
    "post_wp_id": 1986,
    "tag_wp_id": 102
  },
  {
    "post_wp_id": 1986,
    "tag_wp_id": 103
  },
  {
    "post_wp_id": 1986,
    "tag_wp_id": 104
  },
  {
    "post_wp_id": 2013,
    "tag_wp_id": 33
  },
  {
    "post_wp_id": 2013,
    "tag_wp_id": 106
  },
  {
    "post_wp_id": 2041,
    "tag_wp_id": 107
  },
  {
    "post_wp_id": 2041,
    "tag_wp_id": 108
  },
  {
    "post_wp_id": 2078,
    "tag_wp_id": 33
  },
  {
    "post_wp_id": 2078,
    "tag_wp_id": 109
  },
  {
    "post_wp_id": 2145,
    "tag_wp_id": 110
  },
  {
    "post_wp_id": 2145,
    "tag_wp_id": 111
  },
  {
    "post_wp_id": 2145,
    "tag_wp_id": 112
  },
  {
    "post_wp_id": 2193,
    "tag_wp_id": 113
  },
  {
    "post_wp_id": 2193,
    "tag_wp_id": 114
  },
  {
    "post_wp_id": 2218,
    "tag_wp_id": 115
  },
  {
    "post_wp_id": 2218,
    "tag_wp_id": 116
  },
  {
    "post_wp_id": 2278,
    "tag_wp_id": 119
  },
  {
    "post_wp_id": 2278,
    "tag_wp_id": 120
  },
  {
    "post_wp_id": 2524,
    "tag_wp_id": 121
  },
  {
    "post_wp_id": 2524,
    "tag_wp_id": 122
  },
  {
    "post_wp_id": 2544,
    "tag_wp_id": 123
  },
  {
    "post_wp_id": 2544,
    "tag_wp_id": 124
  },
  {
    "post_wp_id": 2635,
    "tag_wp_id": 125
  },
  {
    "post_wp_id": 2635,
    "tag_wp_id": 126
  },
  {
    "post_wp_id": 2678,
    "tag_wp_id": 129
  },
  {
    "post_wp_id": 2678,
    "tag_wp_id": 130
  },
  {
    "post_wp_id": 2705,
    "tag_wp_id": 127
  },
  {
    "post_wp_id": 2739,
    "tag_wp_id": 131
  },
  {
    "post_wp_id": 2770,
    "tag_wp_id": 132
  },
  {
    "post_wp_id": 2770,
    "tag_wp_id": 133
  },
  {
    "post_wp_id": 2863,
    "tag_wp_id": 136
  },
  {
    "post_wp_id": 2863,
    "tag_wp_id": 137
  },
  {
    "post_wp_id": 2900,
    "tag_wp_id": 138
  },
  {
    "post_wp_id": 2900,
    "tag_wp_id": 139
  },
  {
    "post_wp_id": 2929,
    "tag_wp_id": 140
  },
  {
    "post_wp_id": 2929,
    "tag_wp_id": 141
  },
  {
    "post_wp_id": 2971,
    "tag_wp_id": 142
  },
  {
    "post_wp_id": 3001,
    "tag_wp_id": 143
  },
  {
    "post_wp_id": 3195,
    "tag_wp_id": 16
  },
  {
    "post_wp_id": 3195,
    "tag_wp_id": 194
  },
  {
    "post_wp_id": 3293,
    "tag_wp_id": 144
  },
  {
    "post_wp_id": 3293,
    "tag_wp_id": 145
  },
  {
    "post_wp_id": 3713,
    "tag_wp_id": 170
  },
  {
    "post_wp_id": 3713,
    "tag_wp_id": 171
  },
  {
    "post_wp_id": 3747,
    "tag_wp_id": 172
  },
  {
    "post_wp_id": 3747,
    "tag_wp_id": 173
  },
  {
    "post_wp_id": 3785,
    "tag_wp_id": 174
  },
  {
    "post_wp_id": 3831,
    "tag_wp_id": 178
  },
  {
    "post_wp_id": 3899,
    "tag_wp_id": 177
  },
  {
    "post_wp_id": 3975,
    "tag_wp_id": 183
  },
  {
    "post_wp_id": 3978,
    "tag_wp_id": 181
  },
  {
    "post_wp_id": 4074,
    "tag_wp_id": 182
  },
  {
    "post_wp_id": 4171,
    "tag_wp_id": 184
  },
  {
    "post_wp_id": 4481,
    "tag_wp_id": 199
  },
  {
    "post_wp_id": 4505,
    "tag_wp_id": 197
  },
  {
    "post_wp_id": 4505,
    "tag_wp_id": 198
  },
  {
    "post_wp_id": 4545,
    "tag_wp_id": 203
  },
  {
    "post_wp_id": 4629,
    "tag_wp_id": 19
  },
  {
    "post_wp_id": 4817,
    "tag_wp_id": 204
  },
  {
    "post_wp_id": 4878,
    "tag_wp_id": 205
  },
  {
    "post_wp_id": 4985,
    "tag_wp_id": 206
  },
  {
    "post_wp_id": 5006,
    "tag_wp_id": 215
  },
  {
    "post_wp_id": 5065,
    "tag_wp_id": 216
  },
  {
    "post_wp_id": 5099,
    "tag_wp_id": 217
  },
  {
    "post_wp_id": 5104,
    "tag_wp_id": 218
  },
  {
    "post_wp_id": 5147,
    "tag_wp_id": 219
  },
  {
    "post_wp_id": 5148,
    "tag_wp_id": 221
  },
  {
    "post_wp_id": 5149,
    "tag_wp_id": 222
  },
  {
    "post_wp_id": 5153,
    "tag_wp_id": 220
  },
  {
    "post_wp_id": 5412,
    "tag_wp_id": 223
  },
  {
    "post_wp_id": 5432,
    "tag_wp_id": 224
  },
  {
    "post_wp_id": 5464,
    "tag_wp_id": 225
  },
  {
    "post_wp_id": 5509,
    "tag_wp_id": 227
  },
  {
    "post_wp_id": 5525,
    "tag_wp_id": 226
  },
  {
    "post_wp_id": 5559,
    "tag_wp_id": 228
  },
  {
    "post_wp_id": 5562,
    "tag_wp_id": 229
  },
  {
    "post_wp_id": 5568,
    "tag_wp_id": 231
  },
  {
    "post_wp_id": 5703,
    "tag_wp_id": 232
  },
  {
    "post_wp_id": 5704,
    "tag_wp_id": 233
  },
  {
    "post_wp_id": 5794,
    "tag_wp_id": 234
  },
  {
    "post_wp_id": 5800,
    "tag_wp_id": 235
  },
  {
    "post_wp_id": 5879,
    "tag_wp_id": 236
  },
  {
    "post_wp_id": 5882,
    "tag_wp_id": 237
  },
  {
    "post_wp_id": 5888,
    "tag_wp_id": 238
  },
  {
    "post_wp_id": 6067,
    "tag_wp_id": 239
  },
  {
    "post_wp_id": 6106,
    "tag_wp_id": 242
  },
  {
    "post_wp_id": 6123,
    "tag_wp_id": 240
  },
  {
    "post_wp_id": 6125,
    "tag_wp_id": 241
  },
  {
    "post_wp_id": 6183,
    "tag_wp_id": 243
  },
  {
    "post_wp_id": 6186,
    "tag_wp_id": 244
  },
  {
    "post_wp_id": 6319,
    "tag_wp_id": 245
  },
  {
    "post_wp_id": 6327,
    "tag_wp_id": 246
  },
  {
    "post_wp_id": 6331,
    "tag_wp_id": 247
  },
  {
    "post_wp_id": 6388,
    "tag_wp_id": 248
  },
  {
    "post_wp_id": 6400,
    "tag_wp_id": 249
  },
  {
    "post_wp_id": 6405,
    "tag_wp_id": 250
  },
  {
    "post_wp_id": 6501,
    "tag_wp_id": 251
  },
  {
    "post_wp_id": 6512,
    "tag_wp_id": 252
  },
  {
    "post_wp_id": 6517,
    "tag_wp_id": 253
  },
  {
    "post_wp_id": 6655,
    "tag_wp_id": 254
  },
  {
    "post_wp_id": 6668,
    "tag_wp_id": 255
  },
  {
    "post_wp_id": 6676,
    "tag_wp_id": 256
  },
  {
    "post_wp_id": 6760,
    "tag_wp_id": 257
  },
  {
    "post_wp_id": 6770,
    "tag_wp_id": 261
  },
  {
    "post_wp_id": 6793,
    "tag_wp_id": 258
  },
  {
    "post_wp_id": 6943,
    "tag_wp_id": 260
  },
  {
    "post_wp_id": 6946,
    "tag_wp_id": 262
  },
  {
    "post_wp_id": 7012,
    "tag_wp_id": 263
  },
  {
    "post_wp_id": 7014,
    "tag_wp_id": 264
  },
  {
    "post_wp_id": 7058,
    "tag_wp_id": 265
  },
  {
    "post_wp_id": 7133,
    "tag_wp_id": 266
  },
  {
    "post_wp_id": 7142,
    "tag_wp_id": 267
  },
  {
    "post_wp_id": 7165,
    "tag_wp_id": 268
  },
  {
    "post_wp_id": 7198,
    "tag_wp_id": 269
  },
  {
    "post_wp_id": 7201,
    "tag_wp_id": 270
  },
  {
    "post_wp_id": 7207,
    "tag_wp_id": 271
  },
  {
    "post_wp_id": 7239,
    "tag_wp_id": 272
  },
  {
    "post_wp_id": 7389,
    "tag_wp_id": 273
  },
  {
    "post_wp_id": 7464,
    "tag_wp_id": 275
  },
  {
    "post_wp_id": 7468,
    "tag_wp_id": 276
  },
  {
    "post_wp_id": 7506,
    "tag_wp_id": 277
  },
  {
    "post_wp_id": 7531,
    "tag_wp_id": 278
  },
  {
    "post_wp_id": 7543,
    "tag_wp_id": 279
  },
  {
    "post_wp_id": 7549,
    "tag_wp_id": 280
  },
  {
    "post_wp_id": 7619,
    "tag_wp_id": 281
  },
  {
    "post_wp_id": 7645,
    "tag_wp_id": 282
  },
  {
    "post_wp_id": 7649,
    "tag_wp_id": 283
  },
  {
    "post_wp_id": 7712,
    "tag_wp_id": 284
  },
  {
    "post_wp_id": 7719,
    "tag_wp_id": 285
  },
  {
    "post_wp_id": 7723,
    "tag_wp_id": 286
  },
  {
    "post_wp_id": 7781,
    "tag_wp_id": 287
  },
  {
    "post_wp_id": 7785,
    "tag_wp_id": 288
  },
  {
    "post_wp_id": 7788,
    "tag_wp_id": 289
  }
]
